<HBProfile>
///////////////////////////////////////////////////
//                                               //
// Profile generated with ZapRecorder2 v1.2.0    //
// Created by BadWolf                            //
//                                               //
///////////////////////////////////////////////////
<Name>Vale of Eternal Blossoms</Name>
<MinDurability></MinDurability>
<MinFreeBagSlots></MinFreeBagSlots>

<MinLevel>1</MinLevel>
<MaxLevel>91</MaxLevel>
<Factions>99999</Factions>

<MailGrey>false</MailGrey>
<MailWhite>false</MailWhite>
<MailGreen>false</MailGreen>
<MailBlue>false</MailBlue>
<MailPurple>false</MailPurple>

<SellGrey>false</SellGrey>
<SellWhite>false</SellWhite>
<SellGreen>false</SellGreen>
<SellBlue>false</SellBlue>
<SellPurple>false</SellPurple>

<Vendors>
</Vendors>

<Mailboxes>
</Mailboxes>

<Blackspots>
</Blackspots>

<Hotspots>
<Hotspot X="1045.857" Y="467.4716" Z="446.2949" />
<Hotspot X="1046.145" Y="508.696" Z="445.8932" />
<Hotspot X="1044.908" Y="567.5679" Z="443.7546" />
<Hotspot X="1037.907" Y="623.1016" Z="427.9613" />
<Hotspot X="1028.498" Y="680.5445" Z="420.666" />
<Hotspot X="1011.442" Y="735.8281" Z="426.4707" />
<Hotspot X="988.9013" Y="788.1329" Z="438.8543" />
<Hotspot X="966.3067" Y="840.7882" Z="451.3126" />
<Hotspot X="943.7685" Y="893.3121" Z="463.7397" />
<Hotspot X="923.7699" Y="947.1225" Z="472.9695" />
<Hotspot X="910.4656" Y="1003.633" Z="480.1495" />
<Hotspot X="914.6628" Y="1060.375" Z="475.7162" />
<Hotspot X="930.4529" Y="1112.517" Z="454.3986" />
<Hotspot X="944.572" Y="1166.793" Z="438.6896" />
<Hotspot X="981.6114" Y="1210.035" Z="427.2504" />
<Hotspot X="1010.966" Y="1256.664" Z="418.2429" />
<Hotspot X="1010.606" Y="1311.725" Z="400.9371" />
<Hotspot X="1003.747" Y="1365.979" Z="386.7683" />
<Hotspot X="967.7707" Y="1411.915" Z="384.128" />
<Hotspot X="934.691" Y="1459.989" Z="381.1347" />
<Hotspot X="903.7866" Y="1510.102" Z="378.0149" />
<Hotspot X="868.5283" Y="1556.394" Z="375.9059" />
<Hotspot X="819.4473" Y="1584.895" Z="386.2661" />
<Hotspot X="778.2723" Y="1622.759" Z="396.5517" />
<Hotspot X="752.4786" Y="1674.496" Z="399.624" />
<Hotspot X="738.7795" Y="1731.427" Z="397.0475" />
<Hotspot X="744.5505" Y="1788.693" Z="387.1012" />
<Hotspot X="737.9598" Y="1843.778" Z="372.7422" />
<Hotspot X="725.6488" Y="1900.04" Z="359.7368" />
<Hotspot X="715.4811" Y="1956.029" Z="347.9295" />
<Hotspot X="748.558" Y="2001.029" Z="342.5937" />
<Hotspot X="790.1671" Y="2041.747" Z="341.201" />
<Hotspot X="830.9529" Y="2081.427" Z="335.1972" />
<Hotspot X="887.5653" Y="2087.589" Z="325.8289" />
<Hotspot X="944.4252" Y="2087.247" Z="323.125" />
<Hotspot X="1000.414" Y="2105.783" Z="323.5356" />
<Hotspot X="1056.213" Y="2122.619" Z="323.8832" />
<Hotspot X="1100.716" Y="2140.701" Z="328.2871" />
<Hotspot X="1151.114" Y="2168.845" Z="337.5977" />
<Hotspot X="1201.681" Y="2196.997" Z="346.6194" />
<Hotspot X="1257.841" Y="2192.6" Z="358.1819" />
<Hotspot X="1312.591" Y="2198.469" Z="376.3883" />
<Hotspot X="1367.986" Y="2186.053" Z="380.8579" />
<Hotspot X="1358.945" Y="2130.019" Z="380.5187" />
<Hotspot X="1338.357" Y="2075.438" Z="381.3707" />
<Hotspot X="1316.224" Y="2025.475" Z="364.5303" />
<Hotspot X="1278.179" Y="1981.854" Z="357.1208" />
<Hotspot X="1238.003" Y="1940.662" Z="357.8753" />
<Hotspot X="1193.887" Y="1900.255" Z="360.1127" />
<Hotspot X="1152.025" Y="1860.393" Z="362.2745" />
<Hotspot X="1114.819" Y="1814.851" Z="364.1487" />
<Hotspot X="1086.457" Y="1763.394" Z="365.4225" />
<Hotspot X="1061.285" Y="1716.645" Z="366.5734" />
<Hotspot X="1038.315" Y="1673.985" Z="380.0519" />
<Hotspot X="1013.464" Y="1627.831" Z="394.9523" />
<Hotspot X="998.6236" Y="1574.501" Z="397.7979" />
<Hotspot X="1012.34" Y="1520.444" Z="381.4714" />
<Hotspot X="1019.89" Y="1463.303" Z="374.1133" />
<Hotspot X="1030.602" Y="1406.002" Z="378.0652" />
<Hotspot X="1050.323" Y="1351.828" Z="384.476" />
<Hotspot X="1074.221" Y="1311.274" Z="391.1657" />
<Hotspot X="1118.199" Y="1272.555" Z="398.5804" />
<Hotspot X="1173.692" Y="1255.009" Z="403.6752" />
<Hotspot X="1226.86" Y="1231.67" Z="406.6057" />
<Hotspot X="1283.503" Y="1220.087" Z="412.8309" />
<Hotspot X="1341.575" Y="1215.381" Z="422.4242" />
<Hotspot X="1396.649" Y="1201.604" Z="433.8405" />
<Hotspot X="1444.989" Y="1171.426" Z="446.8555" />
<Hotspot X="1452.573" Y="1119.455" Z="457.8527" />
<Hotspot X="1415.061" Y="1083.999" Z="477.7302" />
<Hotspot X="1403.036" Y="1039.212" Z="491.8063" />
<Hotspot X="1382.049" Y="989.9017" Z="473.9613" />
<Hotspot X="1358.935" Y="940.7339" Z="452.3562" />
<Hotspot X="1349.159" Y="885.0812" Z="444.404" />
<Hotspot X="1371.958" Y="832.1873" Z="438.5749" />
<Hotspot X="1407.327" Y="785.3487" Z="441.2317" />
<Hotspot X="1372.813" Y="750.1644" Z="442.8481" />
<Hotspot X="1320.823" Y="726.6703" Z="444.3259" />
<Hotspot X="1285.446" Y="679.8849" Z="442.1495" />
<Hotspot X="1253.616" Y="631.6083" Z="441.0681" />
<Hotspot X="1229.396" Y="578.4828" Z="443.4823" />
</Hotspots>
</HBProfile>
