<HBProfile>
///////////////////////////////////////////////////
//                                               //
// Profile generated with ZapRecorder2 v1.2.0    //
// Created by Guadah                             //
//                                               //
///////////////////////////////////////////////////
<Name>[GB2] [22-25] Pet Training Jade Forest</Name>
<MinDurability>0.4</MinDurability>
<MinFreeBagSlots>1</MinFreeBagSlots>

<MinLevel>1</MinLevel>
<MaxLevel>91</MaxLevel>
<Factions>99999</Factions>

<MailGrey>false</MailGrey>
<MailWhite>false</MailWhite>
<MailGreen>false</MailGreen>
<MailBlue>false</MailBlue>
<MailPurple>false</MailPurple>

<SellGrey>false</SellGrey>
<SellWhite>false</SellWhite>
<SellGreen>false</SellGreen>
<SellBlue>false</SellBlue>
<SellPurple>false</SellPurple>

<Vendors>
</Vendors>

<Mailboxes>
</Mailboxes>

<Blackspots>
</Blackspots>

<Hotspots>
<Hotspot X="-433.6522" Y="-1787.956" Z="71.20587" />
<Hotspot X="-472.0852" Y="-1805.924" Z="69.29875" />
<Hotspot X="-510.6935" Y="-1852.315" Z="60.40278" />
<Hotspot X="-538.9214" Y="-1909.639" Z="63.61307" />
<Hotspot X="-514.2607" Y="-1965.694" Z="64.20327" />
<Hotspot X="-465.4738" Y="-2005.349" Z="62.40001" />
<Hotspot X="-407.8993" Y="-2030.804" Z="62.53495" />
<Hotspot X="-361.8977" Y="-2072.303" Z="63.62418" />
<Hotspot X="-329.1442" Y="-2126.354" Z="62.26452" />
<Hotspot X="-275.528" Y="-2157.56" Z="60.4632" />
<Hotspot X="-233.6361" Y="-2202.579" Z="59.19913" />
<Hotspot X="-214.9341" Y="-2243.68" Z="60.00298" />
<Hotspot X="-221.5874" Y="-2285.827" Z="59.11458" />
<Hotspot X="-237.9177" Y="-2345.926" Z="53.04019" />
<Hotspot X="-264.2022" Y="-2403.494" Z="48.16718" />
<Hotspot X="-303.2206" Y="-2451.502" Z="40.74079" />
<Hotspot X="-356.3132" Y="-2483.51" Z="32.76732" />
<Hotspot X="-418.5912" Y="-2486.251" Z="23.87878" />
<Hotspot X="-476.3245" Y="-2504.695" Z="16.35643" />
<Hotspot X="-496.3684" Y="-2561.157" Z="15.2641" />
<Hotspot X="-479.2251" Y="-2621.971" Z="17.90564" />
<Hotspot X="-447.7345" Y="-2676.281" Z="20.25566" />
<Hotspot X="-405.059" Y="-2722.814" Z="20.58631" />
<Hotspot X="-368.2179" Y="-2774.309" Z="20.59508" />
<Hotspot X="-332.1488" Y="-2825.669" Z="20.56531" />
<Hotspot X="-316.2719" Y="-2885.193" Z="20.7874" />
<Hotspot X="-317.2135" Y="-2948.508" Z="21.7521" />
<Hotspot X="-316.9715" Y="-2990.383" Z="22.39015" />
<Hotspot X="-302.3038" Y="-3029.712" Z="26.48325" />
<Hotspot X="-282.4832" Y="-3087.928" Z="37.87114" />
<Hotspot X="-252.125" Y="-3139.278" Z="50.90864" />
<Hotspot X="-193.6949" Y="-3155.11" Z="62.44699" />
<Hotspot X="-143.3642" Y="-3124.668" Z="54.47469" />
<Hotspot X="-115.6347" Y="-3069.153" Z="45.21172" />
<Hotspot X="-55.69197" Y="-3071.203" Z="53.04201" />
<Hotspot X="2.891866" Y="-3048.289" Z="56.83359" />
<Hotspot X="38.96791" Y="-2999.787" Z="63.45234" />
<Hotspot X="61.24839" Y="-2940.012" Z="68.01986" />
<Hotspot X="71.6576" Y="-2877.734" Z="69.04269" />
<Hotspot X="91.53406" Y="-2818.154" Z="68.95386" />
<Hotspot X="138.7451" Y="-2779.317" Z="63.69611" />
<Hotspot X="188.9294" Y="-2741.39" Z="64.43273" />
<Hotspot X="229.7946" Y="-2693.806" Z="67.14724" />
<Hotspot X="269.7575" Y="-2644.484" Z="69.98072" />
<Hotspot X="306.2684" Y="-2592.691" Z="72.54077" />
<Hotspot X="343.3344" Y="-2541.253" Z="75.16795" />
<Hotspot X="354.6788" Y="-2480.56" Z="75.82313" />
<Hotspot X="333.4806" Y="-2421.584" Z="72.69522" />
<Hotspot X="315.588" Y="-2360.822" Z="73.20379" />
<Hotspot X="324.6308" Y="-2298.758" Z="71.70432" />
<Hotspot X="363.2168" Y="-2252.472" Z="64.18755" />
<Hotspot X="421.9572" Y="-2233.145" Z="52.7356" />
<Hotspot X="476.7699" Y="-2257.087" Z="41.95882" />
<Hotspot X="537.9136" Y="-2243.547" Z="49.99098" />
<Hotspot X="586.2155" Y="-2204.74" Z="60.11127" />
<Hotspot X="610.9468" Y="-2147.522" Z="68.34932" />
<Hotspot X="628.4994" Y="-2087.402" Z="78.11678" />
<Hotspot X="652.5753" Y="-2029.332" Z="87.34214" />
<Hotspot X="686.8576" Y="-1977.261" Z="92.25803" />
<Hotspot X="726.106" Y="-1927.201" Z="92.23991" />
<Hotspot X="768.8937" Y="-1880.834" Z="92.74546" />
<Hotspot X="815.5721" Y="-1839.272" Z="88.72323" />
<Hotspot X="873.3947" Y="-1811.654" Z="85.80623" />
<Hotspot X="936.426" Y="-1810.689" Z="93.36975" />
<Hotspot X="996.6058" Y="-1803.037" Z="107.3975" />
<Hotspot X="1055.423" Y="-1787.453" Z="121.3506" />
<Hotspot X="1115.866" Y="-1788.992" Z="141.4287" />
<Hotspot X="1175.502" Y="-1796.938" Z="162.1918" />
<Hotspot X="1234.011" Y="-1804.798" Z="182.5455" />
<Hotspot X="1292.52" Y="-1801.486" Z="202.7553" />
<Hotspot X="1344.794" Y="-1775.119" Z="220.1068" />
<Hotspot X="1404.413" Y="-1781.612" Z="240.2289" />
<Hotspot X="1434.247" Y="-1833.31" Z="246.4706" />
<Hotspot X="1443.913" Y="-1896.13" Z="243.4641" />
<Hotspot X="1449.834" Y="-1959.08" Z="237.8721" />
<Hotspot X="1457.666" Y="-2021.366" Z="228.4213" />
<Hotspot X="1489.722" Y="-2072.644" Z="211.8115" />
<Hotspot X="1518.766" Y="-2124.897" Z="192.2833" />
<Hotspot X="1535.043" Y="-2183.833" Z="176.1203" />
<Hotspot X="1522.84" Y="-2243.921" Z="165.9018" />
<Hotspot X="1503.75" Y="-2303.39" Z="163.4813" />
<Hotspot X="1462.03" Y="-2351.75" Z="164.0338" />
<Hotspot X="1456.694" Y="-2411.092" Z="166.3883" />
<Hotspot X="1493.608" Y="-2462.954" Z="168.3658" />
<Hotspot X="1548.379" Y="-2491.769" Z="167.073" />
<Hotspot X="1608.036" Y="-2511.187" Z="166.7729" />
<Hotspot X="1671.323" Y="-2507.099" Z="168.3744" />
<Hotspot X="1728.915" Y="-2484.764" Z="174.0711" />
<Hotspot X="1721.635" Y="-2429.244" Z="181.1641" />
<Hotspot X="1705.765" Y="-2368.845" Z="182.8156" />
<Hotspot X="1710.874" Y="-2307.789" Z="188.4438" />
<Hotspot X="1762.559" Y="-2279.021" Z="210.5538" />
<Hotspot X="1809.907" Y="-2244.866" Z="234.2317" />
<Hotspot X="1835.799" Y="-2187.59" Z="238.2577" />
<Hotspot X="1867.632" Y="-2134.842" Z="238.0891" />
<Hotspot X="1927.762" Y="-2125.815" Z="241.9541" />
<Hotspot X="1991.802" Y="-2130.328" Z="246.513" />
<Hotspot X="2053.292" Y="-2142.96" Z="246.4159" />
<Hotspot X="2105.69" Y="-2178.383" Z="245.5429" />
<Hotspot X="2159.048" Y="-2211.406" Z="243.6344" />
<Hotspot X="2211.667" Y="-2244.086" Z="229.6015" />
<Hotspot X="2244.946" Y="-2294.815" Z="213.0723" />
<Hotspot X="2257.103" Y="-2354.799" Z="197.837" />
<Hotspot X="2273.612" Y="-2413.891" Z="181.9683" />
<Hotspot X="2296.051" Y="-2469.862" Z="164.4921" />
<Hotspot X="2324.468" Y="-2522.487" Z="143.024" />
<Hotspot X="2354.905" Y="-2572.882" Z="122.0784" />
<Hotspot X="2411.979" Y="-2588.239" Z="105.8135" />
<Hotspot X="2470.211" Y="-2570.151" Z="91.6564" />
<Hotspot X="2514.982" Y="-2529.127" Z="82.39408" />
<Hotspot X="2536.964" Y="-2470.624" Z="92.95294" />
<Hotspot X="2554.937" Y="-2412.208" Z="109.2984" />
<Hotspot X="2572.963" Y="-2354.292" Z="125.6619" />
<Hotspot X="2590.63" Y="-2296.626" Z="143.6523" />
<Hotspot X="2609.293" Y="-2239.065" Z="162.7025" />
<Hotspot X="2629.426" Y="-2181.472" Z="178.7414" />
<Hotspot X="2646.795" Y="-2122.537" Z="195.3457" />
<Hotspot X="2658.618" Y="-2062.004" Z="208.7238" />
<Hotspot X="2667.419" Y="-2001.5" Z="222.1329" />
<Hotspot X="2694.435" Y="-1946.278" Z="234.4663" />
<Hotspot X="2716.843" Y="-1888.126" Z="244.0565" />
<Hotspot X="2758.045" Y="-1841.685" Z="250.4539" />
<Hotspot X="2810.476" Y="-1807.157" Z="253.2851" />
<Hotspot X="2862.6" Y="-1771.715" Z="251.1901" />
<Hotspot X="2913.658" Y="-1734.354" Z="260.4603" />
<Hotspot X="2941.392" Y="-1680.067" Z="269.707" />
<Hotspot X="2938.667" Y="-1617.53" Z="270.4196" />
<Hotspot X="2938.702" Y="-1554.4" Z="270.8033" />
<Hotspot X="2945.466" Y="-1490.844" Z="269.6032" />
<Hotspot X="2958.522" Y="-1429.007" Z="267.5431" />
<Hotspot X="2972.567" Y="-1367.609" Z="268.4105" />
<Hotspot X="3001.609" Y="-1313.165" Z="257.4136" />
<Hotspot X="3039.78" Y="-1270.776" Z="231.0451" />
<Hotspot X="3098.512" Y="-1267.426" Z="215.5771" />
<Hotspot X="3161.376" Y="-1269.708" Z="214.1328" />
<Hotspot X="3218.846" Y="-1249.815" Z="214.8032" />
<Hotspot X="3217.552" Y="-1186.922" Z="218.6789" />
<Hotspot X="3161.653" Y="-1158.469" Z="224.2626" />
<Hotspot X="3102.444" Y="-1136.624" Z="228.7009" />
<Hotspot X="3044.124" Y="-1112.803" Z="233.6622" />
<Hotspot X="2996.274" Y="-1073.448" Z="244.1864" />
<Hotspot X="2948.311" Y="-1035.328" Z="259.7122" />
<Hotspot X="2927.423" Y="-986.3054" Z="288.889" />
<Hotspot X="2968.754" Y="-963.137" Z="321.6977" />
<Hotspot X="3004.072" Y="-936.9194" Z="344.7146" />
<Hotspot X="3025.162" Y="-880.2349" Z="328.5989" />
<Hotspot X="3039.224" Y="-821.3485" Z="311.8657" />
<Hotspot X="3027.873" Y="-760.7886" Z="302.5269" />
<Hotspot X="3015.69" Y="-699.3433" Z="293.9569" />
<Hotspot X="2962.859" Y="-668.5452" Z="301.7524" />
<Hotspot X="2902.353" Y="-650.3961" Z="298.8284" />
<Hotspot X="2843.196" Y="-631.6848" Z="286.6248" />
<Hotspot X="2783.234" Y="-615.2563" Z="286.5239" />
<Hotspot X="2726.923" Y="-629.85" Z="302.4592" />
<Hotspot X="2667.429" Y="-637.9206" Z="321.1241" />
<Hotspot X="2612.316" Y="-616.2522" Z="343.1366" />
<Hotspot X="2559.54" Y="-580.8749" Z="358.5946" />
<Hotspot X="2500.125" Y="-561.2095" Z="364.7909" />
<Hotspot X="2440.178" Y="-543.3424" Z="360.4044" />
<Hotspot X="2378.422" Y="-528.3682" Z="359.9778" />
<Hotspot X="2320.405" Y="-549.8862" Z="368.4579" />
<Hotspot X="2275.959" Y="-592.7858" Z="379.7828" />
<Hotspot X="2231.04" Y="-637.1672" Z="384.7794" />
<Hotspot X="2177.63" Y="-671.6174" Z="383.7138" />
<Hotspot X="2122.796" Y="-705.239" Z="379.4417" />
<Hotspot X="2067.311" Y="-731.8149" Z="372.6902" />
<Hotspot X="2004.189" Y="-733.35" Z="366.701" />
<Hotspot X="1941.253" Y="-731.3701" Z="360.5524" />
<Hotspot X="1875.912" Y="-730.8523" Z="353.1138" />
<Hotspot X="1813.27" Y="-730.3582" Z="342.9934" />
<Hotspot X="1750.92" Y="-730.1125" Z="333.4654" />
<Hotspot X="1692.588" Y="-748.8099" Z="328.2692" />
<Hotspot X="1643.624" Y="-789.1254" Z="323.6873" />
<Hotspot X="1604.318" Y="-837.226" Z="315.7075" />
<Hotspot X="1567.666" Y="-889.0612" Z="305.8622" />
<Hotspot X="1509.525" Y="-893.7494" Z="293.9057" />
<Hotspot X="1459.106" Y="-858.3165" Z="294.1697" />
<Hotspot X="1433.475" Y="-800.6269" Z="309.3498" />
<Hotspot X="1407.95" Y="-744.2905" Z="322.1733" />
<Hotspot X="1364.682" Y="-701.3792" Z="338.2049" />
<Hotspot X="1303.595" Y="-690.6492" Z="348.7331" />
<Hotspot X="1244.967" Y="-706.8959" Z="358.9922" />
<Hotspot X="1192.453" Y="-743.1876" Z="359.2979" />
<Hotspot X="1144.422" Y="-782.9094" Z="348.2083" />
<Hotspot X="1096.807" Y="-820.057" Z="330.8131" />
<Hotspot X="1067.524" Y="-871.0588" Z="307.1536" />
<Hotspot X="1046.915" Y="-921.3646" Z="275.1644" />
<Hotspot X="1004.43" Y="-954.2565" Z="249.3842" />
<Hotspot X="943.1652" Y="-962.5339" Z="240.6598" />
<Hotspot X="889.1606" Y="-990.9737" Z="226.6699" />
<Hotspot X="848.0455" Y="-1035.422" Z="212.185" />
<Hotspot X="845.6963" Y="-1095.318" Z="197.1497" />
<Hotspot X="822.5615" Y="-1150.884" Z="189.8559" />
<Hotspot X="768.0912" Y="-1181.416" Z="195.8136" />
<Hotspot X="709.3461" Y="-1202.567" Z="199.3148" />
<Hotspot X="652.042" Y="-1227.196" Z="191.9553" />
<Hotspot X="592.8281" Y="-1226.379" Z="171.2648" />
<Hotspot X="541.9767" Y="-1252.093" Z="143.8316" />
<Hotspot X="501.3883" Y="-1269.259" Z="99.09951" />
<Hotspot X="449.3975" Y="-1300.384" Z="84.7286" />
<Hotspot X="402.1503" Y="-1342.293" Z="81.11504" />
<Hotspot X="354.4861" Y="-1384.15" Z="78.0111" />
<Hotspot X="318.1125" Y="-1435.545" Z="76.41611" />
<Hotspot X="274.0927" Y="-1477.005" Z="83.90947" />
<Hotspot X="220.1178" Y="-1506.367" Z="100.4427" />
<Hotspot X="176.7865" Y="-1552.234" Z="105.4226" />
<Hotspot X="143.2932" Y="-1605.637" Z="103.2631" />
<Hotspot X="113.6216" Y="-1661.351" Z="97.65443" />
<Hotspot X="100.0639" Y="-1707.081" Z="76.01737" />
<Hotspot X="73.73373" Y="-1761.894" Z="67.76884" />
<Hotspot X="29.82334" Y="-1806.937" Z="71.43641" />
<Hotspot X="-23.24423" Y="-1840.446" Z="74.64237" />
<Hotspot X="-78.09788" Y="-1872.569" Z="78.36697" />
<Hotspot X="-129.3622" Y="-1907.767" Z="82.46768" />
<Hotspot X="-161.1558" Y="-1961.635" Z="87.17339" />
<Hotspot X="-180.6585" Y="-2022.05" Z="90.93156" />
<Hotspot X="-221.869" Y="-2068.77" Z="87.75111" />
<Hotspot X="-280.462" Y="-2091.285" Z="78.6729" />
<Hotspot X="-320.6438" Y="-2090.981" Z="68.89407" />
</Hotspots>
</HBProfile>
